{
    "metadata": {
        "analysis_timestamp": "\"2025-07-23T08:19:21\"",
        "stems_found": 5,
        "total_analysis_files": 6
    },
    "main_information": {
        "bpm": 108,
        "key": "F",
        "details": {
            "bpm_confidence": 129.19921875,
            "tempo_variations": [
                123.046875,
                123.046875,
                123.046875,
                123.046875,
                123.046875
            ],
            "key_confidence": 0.12436314672231674,
            "chroma_profile": [
                0.39669790863990784,
                0.24743199348449707,
                0.3020334243774414,
                0.22775442898273468,
                0.4185677766799927,
                0.44300520420074463,
                0.2341463267803192,
                0.21462753415107727,
                0.24236446619033813,
                0.4161982238292694,
                0.18801064789295197,
                0.23135238885879517
            ],
            "harmonic_ratio": 0.8166440468157153,
            "percussive_ratio": 0.29169715789500866,
            "spectral_centroid_mean": 2185.5681180236384,
            "spectral_centroid_std": 823.817422742584,
            "spectral_bandwidth_mean": 2328.191272601425,
            "spectral_rolloff_mean": 4567.230715914038,
            "zero_crossing_rate_mean": 0.11195009780742067,
            "rhythm_complexity": 0.24124584225941267,
            "dynamic_range": 0.21094664931297302,
            "loudness_variation": 0.038132257759571075,
            "total_onsets": 384,
            "onset_density": 3.2,
            "estimated_sections": 8,
            "duration_seconds": 120.0
        }
    },
    "audio_quality": {
        "sample_rate": 22050,
        "duration": 266.56512471655327,
        "peak_amplitude": 0.5590775012969971,
        "rms_level": 0.0985984280705452,
        "crest_factor": 5.670247036743,
        "snr_estimate": 8.183501642313624,
        "clipping_ratio": 0.0,
        "bit_depth_estimate": 24
    },
    "genre_and_mood": {
        "main_genre": "Bollywood",
        "sub_genres": [
            "Desi Pop"
        ],
        "genre_confidence": 0.75,
        "moods": [
            {
                "name": "Happy",
                "score": 0.44
            },
            {
                "name": "Romantic",
                "score": 0.38
            },
            {
                "name": "Energetic",
                "score": 0.37
            }
        ],
        "tempo_based_mood": "Medium",
        "harmonic_complexity": 0.24124584225941267
    },
    "vocal_analysis": {
        "presence": "High",
        "gender": "Female",
        "details": {
            "rms_mean": 0.05933414772152901,
            "rms_std": 0.04656703397631645,
            "pitch_mean": 1300.66796875,
            "pitch_std": 949.6904296875,
            "f0_median": 250.3637914461397,
            "f0_mean": 245.07496275882446,
            "f0_std": 107.78683191378671,
            "spectral_centroid_mean": 2682.134340813414,
            "spectral_rolloff_mean": 4405.571260993027,
            "spectral_bandwidth_mean": 2007.4697278025158,
            "mfcc_mean": [
                -343.4848327636719,
                60.49338150024414,
                -16.927846908569336,
                7.887434959411621,
                -5.25244665145874,
                -0.5802454352378845,
                -3.9372384548187256,
                -4.447271347045898,
                -4.0763630867004395,
                -0.5121874809265137,
                -0.6775062680244446,
                6.118491172790527,
                3.632132053375244
            ],
            "vocal_onsets_count": 514,
            "vocal_onset_rate": 1.928234237492814,
            "gender_confidence": 0.7036379144613969,
            "vocal_range_hz": 350.90909090909093,
            "vibrato_detected": true
        }
    },
    "instrument_analysis": {
        "instruments_present": [
            {
                "name": "Bass",
                "file": "bass.wav",
                "presence": "Medium",
                "confidence": 0.5224412307143211,
                "details": {
                    "average_rms": 0.010448824614286423,
                    "rms_std": 0.01397782750427723,
                    "duration_sec": 266.56512471655327,
                    "spectral_centroid_mean": 980.845289891508,
                    "spectral_centroid_std": 1742.4971645433939,
                    "spectral_bandwidth_mean": 1045.191455765542,
                    "spectral_rolloff_mean": 1700.2330978389568,
                    "spectral_contrast_mean": [
                        24.209273157583343,
                        19.550654509681884,
                        19.002265018832695,
                        17.70496548288222,
                        14.852729134973295,
                        14.512204397439861,
                        34.99600752642765
                    ],
                    "zero_crossings_total": 405409,
                    "zero_crossing_rate_mean": 0.06892454959552739,
                    "zero_crossing_rate_std": 0.15042036918854335,
                    "onset_count": 287,
                    "onset_rate": 1.0766599730747815,
                    "onset_strength_mean": 0.1642092764377594,
                    "pitch_mean": 1346.0245361328125,
                    "pitch_std": 1134.722900390625,
                    "pitch_range": 3853.701416015625,
                    "mfcc_mean": [
                        -617.3846435546875,
                        35.18239974975586,
                        30.20139503479004,
                        25.489458084106445,
                        22.10558319091797,
                        19.30853843688965,
                        16.198373794555664,
                        13.404806137084961,
                        10.596075057983398,
                        8.286476135253906,
                        6.476809501647949,
                        5.484351634979248,
                        4.815135955810547
                    ],
                    "mfcc_std": [
                        29.117733001708984,
                        37.83822250366211,
                        32.55674743652344,
                        28.064022064208984,
                        23.46637535095215,
                        20.222476959228516,
                        18.324790954589844,
                        15.134773254394531,
                        12.273004531860352,
                        11.118781089782715,
                        10.329752922058105,
                        9.876581192016602,
                        10.079545021057129
                    ],
                    "chroma_mean": [
                        0.42454996705055237,
                        0.39886072278022766,
                        0.4300120770931244,
                        0.4217950105667114,
                        0.4216980040073395,
                        0.41060855984687805,
                        0.36334073543548584,
                        0.33970385789871216,
                        0.3613205552101135,
                        0.401093989610672,
                        0.3930295705795288,
                        0.3883611261844635
                    ],
                    "activity_ratio": 0.3777545509972999,
                    "dynamic_range": 0.10364232212305069,
                    "energy_distribution": {
                        "low_freq": 302292.15625,
                        "mid_freq": 1047.399658203125,
                        "high_freq": 300.5164794921875
                    },
                    "bass_frequency_ratio": 0.995561661565675
                }
            },
            {
                "name": "Drums",
                "file": "drums.wav",
                "presence": "Medium",
                "confidence": 0.7966972887516022,
                "details": {
                    "average_rms": 0.015933945775032043,
                    "rms_std": 0.01906970515847206,
                    "duration_sec": 266.56512471655327,
                    "spectral_centroid_mean": 3765.100826059436,
                    "spectral_centroid_std": 2196.7197556716997,
                    "spectral_bandwidth_mean": 2530.778202674373,
                    "spectral_rolloff_mean": 6394.668311963108,
                    "spectral_contrast_mean": [
                        23.726530125205414,
                        17.104973963517356,
                        22.28858715166973,
                        24.285287129037894,
                        26.954181831169397,
                        26.689319690647558,
                        47.8702182213163
                    ],
                    "zero_crossings_total": 1495814,
                    "zero_crossing_rate_mean": 0.2543257610399791,
                    "zero_crossing_rate_std": 0.2291929062887295,
                    "onset_count": 783,
                    "onset_rate": 2.9373684979705708,
                    "onset_strength_mean": 1.2188656330108643,
                    "pitch_mean": 2098.267822265625,
                    "pitch_std": 1154.772705078125,
                    "pitch_range": 3854.386962890625,
                    "mfcc_mean": [
                        -483.8842468261719,
                        13.159248352050781,
                        14.878174781799316,
                        10.923128128051758,
                        9.259922981262207,
                        4.100829124450684,
                        5.523905277252197,
                        11.539268493652344,
                        4.2352752685546875,
                        13.784067153930664,
                        3.4387800693511963,
                        1.7227271795272827,
                        2.549461841583252
                    ],
                    "mfcc_std": [
                        115.75796508789062,
                        63.23780059814453,
                        47.18812942504883,
                        30.10679817199707,
                        30.439746856689453,
                        26.492618560791016,
                        26.692852020263672,
                        20.520448684692383,
                        20.177318572998047,
                        18.848031997680664,
                        15.538843154907227,
                        15.532068252563477,
                        15.323548316955566
                    ],
                    "chroma_mean": [
                        0.4071093499660492,
                        0.4060981571674347,
                        0.40829676389694214,
                        0.40100470185279846,
                        0.3736328184604645,
                        0.3738700747489929,
                        0.3576565384864807,
                        0.3645683228969574,
                        0.3904733955860138,
                        0.46920832991600037,
                        0.4186747372150421,
                        0.3773147165775299
                    ],
                    "activity_ratio": 0.4689486978486195,
                    "dynamic_range": 0.12968409061431885,
                    "energy_distribution": {
                        "low_freq": 660525.25,
                        "mid_freq": 417067.59375,
                        "high_freq": 156803.21875
                    },
                    "drum_pattern_complexity": 0.1571215736774999
                }
            },
            {
                "name": "Piano",
                "file": "piano.wav",
                "presence": "Low",
                "confidence": 0.034627370769158006,
                "details": {
                    "average_rms": 0.0006925474153831601,
                    "rms_std": 0.004017966333776712,
                    "duration_sec": 266.56512471655327,
                    "spectral_centroid_mean": 1362.3051046296523,
                    "spectral_centroid_std": 1876.9325323159553,
                    "spectral_bandwidth_mean": 904.8619633269475,
                    "spectral_rolloff_mean": 2296.459565413101,
                    "spectral_contrast_mean": [
                        22.924930144954114,
                        21.597709262807964,
                        22.64470523860033,
                        24.242793179330633,
                        27.74143272318187,
                        24.10336246883191,
                        34.37729917578117
                    ],
                    "zero_crossings_total": 539975,
                    "zero_crossing_rate_mean": 0.09179657729346312,
                    "zero_crossing_rate_std": 0.14913210889137385,
                    "onset_count": 61,
                    "onset_rate": 0.2288371371343612,
                    "onset_strength_mean": 0.043003153055906296,
                    "pitch_mean": 2158.847900390625,
                    "pitch_std": 916.9168090820312,
                    "pitch_range": 3853.821533203125,
                    "mfcc_mean": [
                        -603.5510864257812,
                        2.5614967346191406,
                        -2.093580484390259,
                        0.06931037455797195,
                        2.2970690727233887,
                        0.44480040669441223,
                        -0.6384069323539734,
                        0.7603234648704529,
                        1.3181759119033813,
                        0.10381737351417542,
                        -0.2529540956020355,
                        0.7689552307128906,
                        0.5493417382240295
                    ],
                    "mfcc_std": [
                        17.460792541503906,
                        13.503107070922852,
                        10.050873756408691,
                        8.405928611755371,
                        9.470468521118164,
                        7.435368061065674,
                        6.997931957244873,
                        5.984840393066406,
                        5.596342086791992,
                        5.218249320983887,
                        3.753002405166626,
                        5.438553810119629,
                        4.130537986755371
                    ],
                    "chroma_mean": [
                        0.15927021205425262,
                        0.18740777671337128,
                        0.1588391810655594,
                        0.13432824611663818,
                        0.1198100745677948,
                        0.11215318739414215,
                        0.11785978823900223,
                        0.10283887386322021,
                        0.11559002846479416,
                        0.11312524974346161,
                        0.11905325949192047,
                        0.13070622086524963
                    ],
                    "activity_ratio": 0.0189878930406759,
                    "dynamic_range": 0.11981955170631409,
                    "energy_distribution": {
                        "low_freq": 23836.0703125,
                        "mid_freq": 986.7178344726562,
                        "high_freq": 109.6491470336914
                    }
                }
            },
            {
                "name": "Other",
                "file": "other.wav",
                "presence": "High",
                "confidence": 1.0,
                "details": {
                    "average_rms": 0.034758977591991425,
                    "rms_std": 0.03565969690680504,
                    "duration_sec": 266.56512471655327,
                    "spectral_centroid_mean": 2262.428363585714,
                    "spectral_centroid_std": 1079.1261847108726,
                    "spectral_bandwidth_mean": 1740.3539738880213,
                    "spectral_rolloff_mean": 4042.4814320432943,
                    "spectral_contrast_mean": [
                        22.562476031088533,
                        19.366219089175463,
                        27.261983124557577,
                        28.657455973967096,
                        29.555167731985065,
                        32.390250753600945,
                        57.58855767270045
                    ],
                    "zero_crossings_total": 910599,
                    "zero_crossing_rate_mean": 0.15482789840279593,
                    "zero_crossing_rate_std": 0.10290722603926034,
                    "onset_count": 487,
                    "onset_rate": 1.8269456685972771,
                    "onset_strength_mean": 1.0375685691833496,
                    "pitch_mean": 1531.5150146484375,
                    "pitch_std": 1047.3946533203125,
                    "pitch_range": 3854.236328125,
                    "mfcc_mean": [
                        -358.49981689453125,
                        68.15276336669922,
                        -26.41132164001465,
                        9.36381721496582,
                        -9.851156234741211,
                        -1.9022477865219116,
                        -6.414754390716553,
                        -0.43419086933135986,
                        -3.674391269683838,
                        -1.0713859796524048,
                        -3.4462356567382812,
                        -2.4510486125946045,
                        -8.110307693481445
                    ],
                    "mfcc_std": [
                        134.42437744140625,
                        60.65161895751953,
                        38.606361389160156,
                        30.99336051940918,
                        28.360795974731445,
                        23.94713020324707,
                        22.281780242919922,
                        21.463605880737305,
                        20.675424575805664,
                        18.760692596435547,
                        18.020463943481445,
                        17.557161331176758,
                        16.009044647216797
                    ],
                    "chroma_mean": [
                        0.3305663764476776,
                        0.1669035404920578,
                        0.22896131873130798,
                        0.15396490693092346,
                        0.3111321032047272,
                        0.377855122089386,
                        0.15578770637512207,
                        0.155776247382164,
                        0.22382596135139465,
                        0.4966200590133667,
                        0.16619561612606049,
                        0.16648758947849274
                    ],
                    "activity_ratio": 0.7091716749412073,
                    "dynamic_range": 0.20830443501472473,
                    "energy_distribution": {
                        "low_freq": 2186977.25,
                        "mid_freq": 854478.3125,
                        "high_freq": 85863.7734375
                    }
                }
            },
            {
                "name": "Vocals",
                "file": "vocals.wav",
                "presence": "High",
                "confidence": 1.0,
                "details": {
                    "average_rms": 0.05933414772152901,
                    "rms_std": 0.04656703397631645,
                    "duration_sec": 266.56512471655327,
                    "spectral_centroid_mean": 2682.134340813414,
                    "spectral_centroid_std": 2344.748004088537,
                    "spectral_bandwidth_mean": 2007.4697278025158,
                    "spectral_rolloff_mean": 4405.571260993027,
                    "spectral_contrast_mean": [
                        27.124632808462295,
                        18.63695593897887,
                        22.34834059887422,
                        22.866740443253185,
                        24.415896468395648,
                        27.561524346708424,
                        49.69463698941523
                    ],
                    "zero_crossings_total": 1005830,
                    "zero_crossing_rate_mean": 0.17102160294726068,
                    "zero_crossing_rate_std": 0.22108251567278336,
                    "onset_count": 514,
                    "onset_rate": 1.928234237492814,
                    "onset_strength_mean": 1.0748248100280762,
                    "pitch_mean": 1300.66796875,
                    "pitch_std": 949.6904296875,
                    "pitch_range": 3854.185546875,
                    "mfcc_mean": [
                        -343.4848327636719,
                        60.49338150024414,
                        -16.927846908569336,
                        7.887434959411621,
                        -5.25244665145874,
                        -0.5802454352378845,
                        -3.9372384548187256,
                        -4.447271347045898,
                        -4.0763630867004395,
                        -0.5121874809265137,
                        -0.6775062680244446,
                        6.118491172790527,
                        3.632132053375244
                    ],
                    "mfcc_std": [
                        151.327880859375,
                        75.94750213623047,
                        46.362159729003906,
                        31.5383243560791,
                        29.09927749633789,
                        22.950376510620117,
                        19.331336975097656,
                        21.507781982421875,
                        17.766307830810547,
                        15.649612426757812,
                        15.622776985168457,
                        18.660112380981445,
                        20.523937225341797
                    ],
                    "chroma_mean": [
                        0.38483086228370667,
                        0.3300582766532898,
                        0.3886398375034332,
                        0.3422769010066986,
                        0.3473435640335083,
                        0.37072259187698364,
                        0.2859184145927429,
                        0.2905811369419098,
                        0.26516467332839966,
                        0.3103734850883484,
                        0.22873079776763916,
                        0.2845405638217926
                    ],
                    "activity_ratio": 0.7782423133873356,
                    "dynamic_range": 0.21938751637935638,
                    "energy_distribution": {
                        "low_freq": 3603011.25,
                        "mid_freq": 979125.375,
                        "high_freq": 135785.90625
                    }
                }
            }
        ],
        "instrument_count": 4,
        "dominant_instrument": "Other"
    },
    "advanced_analysis": {
        "stem_correlations": {
            "bass.wav_vs_drums.wav": 0.011779413000378955,
            "bass.wav_vs_other.wav": 0.025536984363104503,
            "bass.wav_vs_piano.wav": 0.008636708582765967,
            "bass.wav_vs_vocals.wav": 0.07070758014354066,
            "drums.wav_vs_other.wav": 0.028768430607466238,
            "drums.wav_vs_piano.wav": 0.0935344710831884,
            "drums.wav_vs_vocals.wav": 0.04201334769251525,
            "other.wav_vs_piano.wav": 0.025266362532141283,
            "other.wav_vs_vocals.wav": 0.04004900518903058,
            "piano.wav_vs_vocals.wav": 0.02670065886028141
        },
        "mix_balance": {
            "vocal_prominence": 0.05933414772152901,
            "instrument_balance": [
                {
                    "name": "Bass",
                    "level": 0.010448824614286423
                },
                {
                    "name": "Drums",
                    "level": 0.015933945775032043
                },
                {
                    "name": "Piano",
                    "level": 0.0006925474153831601
                },
                {
                    "name": "Other",
                    "level": 0.034758977591991425
                },
                {
                    "name": "Vocals",
                    "level": 0.05933414772152901
                }
            ]
        },
        "production_quality": {
            "dynamic_range": 5.670247036743,
            "mastering_level": "Professional",
            "stereo_imaging": "Estimated based on spectral analysis"
        }
    }
}